{
  "WILDLIFE": {
    "Normal": [
      [
        "Numbat",
        "Ichthyology",
        "Albatross",
        "Dragonfly",
        "Vulture",
        "Aquatic",
        "Crane",
        "Whale",
        "Raven",
        "Raccoon"
      ],
      [
        "Crocodile",
        "Ecology",
        "Fauna",
        "Peacock",
        "Lapwing",
        "Lionfish",
        "Adaptation",
        "Symbiosis",
        "Buzzard",
        "Swift"
      ],
      [
        "Salamander",
        "Llama",
        "Octopus",
        "Shovelnose",
        "Armadillo",
        "Marine",
        "Species",
        "Honeybee",
        "Parrot",
        "Deer"
      ],
      [
        "Elephants",
        "Jackrabbit",
        "Rainforest",
        "Platypus",
        "Duck",
        "Habitat",
        "Stingray",
        "Quail",
        "Basset",
        "Botany"
      ],
      [
        "Hackleback",
        "Alligator",
        "Cockroach",
        "Numbfish",
        "Walrus",
        "Lemur",
        "Narwhal",
        "Reptiles",
        "Marmot",
        "Bison"
      ],
      [
        "Caddisfly",
        "Zoology",
        "Mudpuppy",
        "Wilderness",
        "Hornet",
        "Ibizan",
        "Goat",
        "Squirrel",
        "Prey",
        "Skunk"
      ],
      [
        "Marmoset",
        "Chinchilla",
        "Savanna",
        "Hyena",
        "Iguana",
        "Ecosystem",
        "Appaloosa",
        "Snail",
        "Sparrow",
        "Mammals"
      ],
      [
        "Clownfish",
        "Bear",
        "Extinction",
        "Caribou",
        "Orangutan",
        "Liger",
        "Thresher",
        "Bullfrog",
        "Pigeon",
        "Koala"
      ],
      [
        "Herpetology",
        "Butterfly",
        "Wasp",
        "Bearcat",
        "Monkey",
        "Magpie",
        "Capybara",
        "Zebra",
        "Camel",
        "Snake"
      ],
      [
        "Seagull",
        "Diurnal",
        "Wallaby",
        "Migration",
        "Scorpion",
        "Birdie",
        "Dove",
        "Weasel",
        "Parakeet",
        "Curlew"
      ]
    ],
    "Hard": [
      [
        "Biodiversity",
        "Kingfisher",
        "Dromedary",
        "Camouflage",
        "Jaguar",
        "Predator",
        "Ornithology",
        "Ladybug",
        "Hummingbird",
        "Dugong",
        "Coyote",
        "Naturalist",
        "Kestrel",
        "Woodpecker",
        "Forest"
      ],
      [
        "Tarpon",
        "Sanctuary",
        "Trogon",
        "Panther",
        "Neddicky",
        "Buffalo",
        "Serval",
        "Tigerfish",
        "Tortoise",
        "Cheetah",
        "Parrotfish",
        "Rabbit",
        "Meerkat",
        "Antelope",
        "Giraffe"
      ],
      [
        "Wetlands",
        "Redfish",
        "Insects",
        "Impala",
        "Neanderthal",
        "Nocturnal",
        "Gerbil",
        "Poaching",
        "Ocelot",
        "Salmon",
        "Axolotl",
        "Reforestation",
        "Donkey",
        "Geckos",
        "Firefly"
      ],
      [
        "Endangered",
        "Binturong",
        "Beetle",
        "Reindeer",
        "Rhinoceros",
        "Manatee",
        "Caiman",
        "Goldfish",
        "Camelopard",
        "Porcupine",
        "Ostrich",
        "Kangaroo",
        "Indigo",
        "Jackal",
        "Elephant"
      ],
      [
        "Lizard",
        "Mantis",
        "Cormorant",
        "Monitor",
        "Gibbon",
        "Grasshopper",
        "Anglerfish",
        "Mammalogy",
        "Anemonefish",
        "Jungle",
        "Roadrunner",
        "Tundra",
        "Spider",
        "Anaconda",
        "Amphibians"
      ]
    ],
    "Bonus": {
      "Normal": [
        [
          "Sloth",
          "Gull",
          "Leech",
          "Seal",
          "Kiwi",
          "Lynx",
          "Finch",
          "Crab",
          "Harpy",
          "Chimp"
        ]
      ],
      "Hard": [
        [
          "Hyacinth",
          "Shrimp",
          "Entomology",
          "Conservation",
          "Kookaburra",
          "Oystercatcher",
          "Falcon",
          "Arboreal",
          "Barnacle",
          "Ranger",
          "Yellowtail",
          "Piranha",
          "Barracuda",
          "Caracal",
          "Hedgehog"
        ]
      ]
    }
  }
}